fluidsim/magic.py
fluidsim/build_conf.txt
fluidsim/_version.py
fluidsim/__init__.py
fluidsim/operators/op_finitediff1d.py
fluidsim/operators/op_finitediff2d.py
fluidsim/operators/operators2d.py
fluidsim/operators/__init__.py
fluidsim/operators/operators3d.py
fluidsim/operators/operators1d.py
fluidsim/operators/operators0d.py
fluidsim/operators/sphericalharmo.py
fluidsim/operators/base.py
fluidsim/operators/test/test_operators2d.py
fluidsim/operators/test/test_operators3d.py
fluidsim/operators/test/__init__.py
fluidsim/operators/__python__/operators2d.py
fluidsim/operators/__python__/operators3d.py
fluidsim/operators/__pythran__/operators3d.cpython-314t-darwin.so
fluidsim/operators/__pythran__/operators2d.cpython-314t-darwin.so
fluidsim/operators/__numba__/operators2d.py
fluidsim/operators/__numba__/operators3d.py
fluidsim/util/util.py
fluidsim/util/mini_oper_modif_resol.py
fluidsim/util/__init__.py
fluidsim/util/test_util.py
fluidsim/util/test_phys_fields.py
fluidsim/util/frequency_modulation.py
fluidsim/util/testing.py
fluidsim/util/phys_fields.py
fluidsim/util/__python__/mini_oper_modif_resol.py
fluidsim/util/__pythran__/mini_oper_modif_resol.cpython-314t-darwin.so
fluidsim/util/scripts/test_ipy_load.py
fluidsim/util/scripts/__init__.py
fluidsim/util/scripts/turb_trandom_anisotropic.py
fluidsim/util/scripts/ipy_load.py
fluidsim/util/scripts/test_modif_resolution.py
fluidsim/util/scripts/restart.py
fluidsim/util/scripts/test_turb_trandom_anisotropic.py
fluidsim/util/scripts/test_restart.py
fluidsim/util/scripts/modif_resolution.py
fluidsim/util/__numba__/mini_oper_modif_resol.py
fluidsim/util/console/test_bench.py
fluidsim/util/console/bench_analysis.py
fluidsim/util/console/util.py
fluidsim/util/console/profile.py
fluidsim/util/console/__init__.py
fluidsim/util/console/test_profile.py
fluidsim/util/console/bench.py
fluidsim/util/console/__main__.py
fluidsim/extend_simul/__init__.py
fluidsim-0.9.0.dist-info/RECORD
fluidsim-0.9.0.dist-info/WHEEL
fluidsim-0.9.0.dist-info/entry_points.txt
fluidsim-0.9.0.dist-info/METADATA
fluidsim-0.9.0.dist-info/licenses/LICENSE.txt
