Metadata-Version: 2.4
Name: fluidsim
Version: 0.9.0
Summary: Framework for studying fluid dynamics with simulations.
Keywords: Fluid dynamics,research
Author-Email: "pierre.augier" <pierre.augier@univ-grenoble-alpes.fr>
License-Expression: CECILL-2.1
License-File: LICENSE.txt
Classifier: Development Status :: 5 - Production/Stable
Classifier: Intended Audience :: Science/Research
Classifier: Intended Audience :: Education
Classifier: Topic :: Scientific/Engineering
Classifier: Programming Language :: Python
Classifier: Programming Language :: Python :: 3
Classifier: Programming Language :: Python :: 3.11
Classifier: Programming Language :: Python :: 3.12
Classifier: Programming Language :: Python :: 3.13
Classifier: Programming Language :: Python :: 3.14
Project-URL: Source, https://foss.heptapod.net/fluiddyn/fluidsim
Project-URL: Documentation, https://fluidsim.readthedocs.io
Project-URL: Git Mirror, https://github.com/fluiddyn/fluidsim
Requires-Python: >=3.11
Requires-Dist: fluidsim-core<0.9.1,>=0.8.6
Requires-Dist: h5py
Requires-Dist: h5netcdf
Requires-Dist: transonic>=0.6.2
Requires-Dist: xarray
Requires-Dist: rich
Requires-Dist: matplotlib>=3.3
Requires-Dist: scipy
Provides-Extra: fft
Requires-Dist: pyfftw>=0.10.4; extra == "fft"
Requires-Dist: fluidfft>=0.4.0; extra == "fft"
Provides-Extra: mpi
Requires-Dist: mpi4py; extra == "mpi"
Provides-Extra: test
Requires-Dist: pytest; extra == "test"
Requires-Dist: coverage; extra == "test"
Requires-Dist: pytest-cov; extra == "test"
Requires-Dist: pytest-allclose; extra == "test"
Requires-Dist: pytest-mock; extra == "test"
Requires-Dist: ipython; extra == "test"
Requires-Dist: pymech; extra == "test"
Provides-Extra: test-mpi
Requires-Dist: fluidsim[test]; extra == "test-mpi"
Requires-Dist: pytest-mpi; extra == "test-mpi"
Provides-Extra: pulp
Requires-Dist: pulp; extra == "pulp"
